{
    "data": [
        {
            "underlying": "BANKNIFTY",
            "identifier": "FUTIDXBANKNIFTY31-03-2022XX0.00",
            "instrumentType": "FUTIDX",
            "instrument": "Index Futures",
            "contract": "BANKNIFTY 31-Mar-2022",
            "expiryDate": "31-Mar-2022",
            "optionType": "-",
            "strikePrice": 0,
            "lastPrice": 35166.65,
            "change": -392.15,
            "pChange": -1.1,
            "volume": 1297550,
            "totalTurnover": 45698724862,
            "value": 45698724862,
            "premiumTurnOver": 45698724862,
            "underlyingValue": 35060.85,
            "openInterest": 91239,
            "noOfTrades": 51730,
            "meta": {
                "data": [],
                "msg": "No Data Found"
            }
        },
        {
            "underlying": "BANKNIFTY",
            "identifier": "FUTIDXBANKNIFTY28-04-2022XX0.00",
            "instrumentType": "FUTIDX",
            "instrument": "Index Futures",
            "contract": "BANKNIFTY 28-Apr-2022",
            "expiryDate": "28-Apr-2022",
            "optionType": "-",
            "strikePrice": 0,
            "lastPrice": 35283.65,
            "change": -381,
            "pChange": -1.07,
            "volume": 309350,
            "totalTurnover": 10927680477.5,
            "value": 10927680477.5,
            "premiumTurnOver": 10927680477.5,
            "underlyingValue": 35060.85,
            "openInterest": 103673,
            "noOfTrades": 12298,
            "meta": {
                "data": [],
                "msg": "No Data Found"
            }
        },
        {
            "underlying": "BANKNIFTY",
            "identifier": "FUTIDXBANKNIFTY26-05-2022XX0.00",
            "instrumentType": "FUTIDX",
            "instrument": "Index Futures",
            "contract": "BANKNIFTY 26-May-2022",
            "expiryDate": "26-May-2022",
            "optionType": "-",
            "strikePrice": 0,
            "lastPrice": 35405,
            "change": -389.55,
            "pChange": -1.09,
            "volume": 87225,
            "totalTurnover": 3090549222,
            "value": 3090549222,
            "premiumTurnOver": 3090549222,
            "underlyingValue": 35060.85,
            "openInterest": 79727,
            "noOfTrades": 3484,
            "meta": {
                "data": [],
                "msg": "No Data Found"
            }
        }
    ],
    "timestamp": "28-Mar-2022 10:44:49",
    "marketStatus": {
        "market": "FO",
        "marketOpenOrClose": "Open",
        "marketCurrentTradingDate": "Mar 28,2022",
        "marketOpenTime": "0915",
        "marketCloseTime": "1530",
        "marketPreviousTradingDate": "Mar 25,2022",
        "marketNextTradingDate": "Mar 29,2022",
        "marketStatusMessage": "Market is Open"
    }
}