{
    "data": [
        {
            "underlying": "BANKNIFTY",
            "identifier": "FUTIDXBANKNIFTY31-03-2022XX0.00",
            "instrumentType": "FUTIDX",
            "instrument": "Index Futures",
            "contract": "BANKNIFTY 31-Mar-2022",
            "expiryDate": "31-Mar-2022",
            "optionType": "-",
            "strikePrice": 0,
            "lastPrice": 35254.6,
            "change": -208.8,
            "pChange": -0.59,
            "volume": 1942550,
            "totalTurnover": 68882958978.5,
            "value": 68882958978.5,
            "premiumTurnOver": 68882958978.5,
            "underlyingValue": 35170.7,
            "openInterest": 103987,
            "noOfTrades": 77395,
            "meta": {
                "data": [],
                "msg": "No Data Found"
            }
        },
        {
            "underlying": "BANKNIFTY",
            "identifier": "FUTIDXBANKNIFTY28-04-2022XX0.00",
            "instrumentType": "FUTIDX",
            "instrument": "Index Futures",
            "contract": "BANKNIFTY 28-Apr-2022",
            "expiryDate": "28-Apr-2022",
            "optionType": "-",
            "strikePrice": 0,
            "lastPrice": 35398.9,
            "change": -101.3,
            "pChange": -0.29,
            "volume": 76425,
            "totalTurnover": 2719055528.2499995,
            "value": 2719055528.2499995,
            "premiumTurnOver": 2719055528.2499995,
            "underlyingValue": 35170.7,
            "openInterest": 33966,
            "noOfTrades": 3025,
            "meta": {
                "data": [],
                "msg": "No Data Found"
            }
        },
        {
            "underlying": "BANKNIFTY",
            "identifier": "FUTIDXBANKNIFTY26-05-2022XX0.00",
            "instrumentType": "FUTIDX",
            "instrument": "Index Futures",
            "contract": "BANKNIFTY 26-May-2022",
            "expiryDate": "26-May-2022",
            "optionType": "-",
            "strikePrice": 0,
            "lastPrice": 35520,
            "change": -58.6,
            "pChange": -0.16,
            "volume": 23400,
            "totalTurnover": 836166941.9999999,
            "value": 836166941.9999999,
            "premiumTurnOver": 836166941.9999999,
            "underlyingValue": 35170.7,
            "openInterest": 28955,
            "noOfTrades": 932,
            "meta": {
                "data": [],
                "msg": "No Data Found"
            }
        }
    ],
    "timestamp": "03-Mar-2022 11:06:22",
    "marketStatus": {
        "market": "FO",
        "marketOpenOrClose": "Open",
        "marketCurrentTradingDate": "Mar 03,2022",
        "marketOpenTime": "0915",
        "marketCloseTime": "1530",
        "marketPreviousTradingDate": "Mar 02,2022",
        "marketNextTradingDate": "Mar 04,2022",
        "marketStatusMessage": "Market is Open"
    }
}