{
    "data": [
        {
            "underlying": "BANKNIFTY",
            "identifier": "FUTIDXBANKNIFTY28-04-2022XX0.00",
            "instrumentType": "FUTIDX",
            "instrument": "Index Futures",
            "contract": "BANKNIFTY 28-Apr-2022",
            "expiryDate": "28-Apr-2022",
            "optionType": "-",
            "strikePrice": 0,
            "lastPrice": 36469.3,
            "change": 66.1,
            "pChange": 0.18,
            "volume": 2945675,
            "totalTurnover": 107367615037,
            "value": 107367615037,
            "premiumTurnOver": 107367615037,
            "underlyingValue": 36375.45,
            "openInterest": 90077,
            "noOfTrades": 117537,
            "meta": {
                "data": [],
                "msg": "No Data Found"
            }
        },
        {
            "underlying": "BANKNIFTY",
            "identifier": "FUTIDXBANKNIFTY26-05-2022XX0.00",
            "instrumentType": "FUTIDX",
            "instrument": "Index Futures",
            "contract": "BANKNIFTY 26-May-2022",
            "expiryDate": "26-May-2022",
            "optionType": "-",
            "strikePrice": 0,
            "lastPrice": 36602,
            "change": 92.9,
            "pChange": 0.25,
            "volume": 222275,
            "totalTurnover": 8124962553.75,
            "value": 8124962553.75,
            "premiumTurnOver": 8124962553.75,
            "underlyingValue": 36375.45,
            "openInterest": 16600,
            "noOfTrades": 8885,
            "meta": {
                "data": [],
                "msg": "No Data Found"
            }
        },
        {
            "underlying": "BANKNIFTY",
            "identifier": "FUTIDXBANKNIFTY30-06-2022XX0.00",
            "instrumentType": "FUTIDX",
            "instrument": "Index Futures",
            "contract": "BANKNIFTY 30-Jun-2022",
            "expiryDate": "30-Jun-2022",
            "optionType": "-",
            "strikePrice": 0,
            "lastPrice": 36699,
            "change": 60.2,
            "pChange": 0.16,
            "volume": 39775,
            "totalTurnover": 1459374183.5,
            "value": 1459374183.5,
            "premiumTurnOver": 1459374183.5,
            "underlyingValue": 36375.45,
            "openInterest": 3595,
            "noOfTrades": 1591,
            "meta": {
                "data": [],
                "msg": "No Data Found"
            }
        }
    ],
    "timestamp": "20-Apr-2022 13:28:22",
    "marketStatus": {
        "market": "FO",
        "marketOpenOrClose": "Open",
        "marketCurrentTradingDate": "Apr 20,2022",
        "marketOpenTime": "0915",
        "marketCloseTime": "1530",
        "marketPreviousTradingDate": "Apr 19,2022",
        "marketNextTradingDate": "Apr 21,2022",
        "marketStatusMessage": "Market is Open"
    }
}