{
    "data": [
        {
            "underlying": "BANKNIFTY",
            "identifier": "FUTIDXBANKNIFTY28-04-2022XX0.00",
            "instrumentType": "FUTIDX",
            "instrument": "Index Futures",
            "contract": "BANKNIFTY 28-Apr-2022",
            "expiryDate": "28-Apr-2022",
            "optionType": "-",
            "strikePrice": 0,
            "lastPrice": 36410.9,
            "change": 260.55,
            "pChange": 0.72,
            "volume": 2845825,
            "totalTurnover": 103876084406.5,
            "value": 103876084406.5,
            "premiumTurnOver": 103876084406.5,
            "underlyingValue": 36397.05,
            "openInterest": 70399,
            "noOfTrades": 112921,
            "meta": {
                "data": [],
                "msg": "No Data Found"
            }
        },
        {
            "underlying": "BANKNIFTY",
            "identifier": "FUTIDXBANKNIFTY26-05-2022XX0.00",
            "instrumentType": "FUTIDX",
            "instrument": "Index Futures",
            "contract": "BANKNIFTY 26-May-2022",
            "expiryDate": "26-May-2022",
            "optionType": "-",
            "strikePrice": 0,
            "lastPrice": 36434.95,
            "change": 270.9,
            "pChange": 0.75,
            "volume": 965725,
            "totalTurnover": 35273685060,
            "value": 35273685060,
            "premiumTurnOver": 35273685060,
            "underlyingValue": 36397,
            "openInterest": 63098,
            "noOfTrades": 38385,
            "meta": {
                "data": [],
                "msg": "No Data Found"
            }
        },
        {
            "underlying": "BANKNIFTY",
            "identifier": "FUTIDXBANKNIFTY30-06-2022XX0.00",
            "instrumentType": "FUTIDX",
            "instrument": "Index Futures",
            "contract": "BANKNIFTY 30-Jun-2022",
            "expiryDate": "30-Jun-2022",
            "optionType": "-",
            "strikePrice": 0,
            "lastPrice": 36555,
            "change": 235.35,
            "pChange": 0.65,
            "volume": 64550,
            "totalTurnover": 2365838833,
            "value": 2365838833,
            "premiumTurnOver": 2365838833,
            "underlyingValue": 36397.05,
            "openInterest": 4465,
            "noOfTrades": 2544,
            "meta": {
                "data": [],
                "msg": "No Data Found"
            }
        }
    ],
    "timestamp": "26-Apr-2022 14:29:22",
    "marketStatus": {
        "market": "FO",
        "marketOpenOrClose": "Open",
        "marketCurrentTradingDate": "Apr 26,2022",
        "marketOpenTime": "0915",
        "marketCloseTime": "1530",
        "marketPreviousTradingDate": "Apr 25,2022",
        "marketNextTradingDate": "Apr 27,2022",
        "marketStatusMessage": "Market is Open"
    }
}