{
    "data": [
        {
            "underlying": "FINNIFTY",
            "identifier": "OPTIDXFINNIFTY05-04-2022CE17500.00",
            "instrumentType": "OPTIDX",
            "instrument": "Index Options",
            "contract": "FINNIFTY 05-Apr-2022",
            "expiryDate": "05-Apr-2022",
            "optionType": "Call",
            "strikePrice": 17500,
            "lastPrice": 101.9,
            "change": 7.25,
            "pChange": 7.66,
            "volume": 3000,
            "totalTurnover": 310440,
            "value": 310440,
            "premiumTurnOver": 52810440,
            "underlyingValue": 17235.7,
            "openInterest": 101,
            "noOfTrades": 75
        },
        {
            "underlying": "FINNIFTY",
            "identifier": "OPTIDXFINNIFTY05-04-2022PE16000.00",
            "instrumentType": "OPTIDX",
            "instrument": "Index Options",
            "contract": "FINNIFTY 05-Apr-2022",
            "expiryDate": "05-Apr-2022",
            "optionType": "Put",
            "strikePrice": 16000,
            "lastPrice": 8.6,
            "change": -3.8,
            "pChange": -30.65,
            "volume": 1840,
            "totalTurnover": 30985.6,
            "value": 30985.6,
            "premiumTurnOver": 29470985.6,
            "underlyingValue": 17235.7,
            "openInterest": 45,
            "noOfTrades": 46
        },
        {
            "underlying": "FINNIFTY",
            "identifier": "OPTIDXFINNIFTY05-04-2022CE18000.00",
            "instrumentType": "OPTIDX",
            "instrument": "Index Options",
            "contract": "FINNIFTY 05-Apr-2022",
            "expiryDate": "05-Apr-2022",
            "optionType": "Call",
            "strikePrice": 18000,
            "lastPrice": 17.1,
            "change": -2.8,
            "pChange": -14.07,
            "volume": 1320,
            "totalTurnover": 22004.4,
            "value": 22004.4,
            "premiumTurnOver": 23782004.4,
            "underlyingValue": 17235.7,
            "openInterest": 25,
            "noOfTrades": 33
        },
        {
            "underlying": "FINNIFTY",
            "identifier": "OPTIDXFINNIFTY05-04-2022CE17600.00",
            "instrumentType": "OPTIDX",
            "instrument": "Index Options",
            "contract": "FINNIFTY 05-Apr-2022",
            "expiryDate": "05-Apr-2022",
            "optionType": "Call",
            "strikePrice": 17600,
            "lastPrice": 66.1,
            "change": 2.1,
            "pChange": 3.28,
            "volume": 880,
            "totalTurnover": 72996,
            "value": 72996,
            "premiumTurnOver": 15560996,
            "underlyingValue": 17235.7,
            "openInterest": 7,
            "noOfTrades": 22
        },
        {
            "underlying": "FINNIFTY",
            "identifier": "OPTIDXFINNIFTY05-04-2022CE17700.00",
            "instrumentType": "OPTIDX",
            "instrument": "Index Options",
            "contract": "FINNIFTY 05-Apr-2022",
            "expiryDate": "05-Apr-2022",
            "optionType": "Call",
            "strikePrice": 17700,
            "lastPrice": 59.95,
            "change": 4.65,
            "pChange": 8.41,
            "volume": 240,
            "totalTurnover": 16886.4,
            "value": 16886.4,
            "premiumTurnOver": 4264886.4,
            "underlyingValue": 17235.7,
            "openInterest": 2,
            "noOfTrades": 6
        },
        {
            "underlying": "FINNIFTY",
            "identifier": "OPTIDXFINNIFTY05-04-2022PE16500.00",
            "instrumentType": "OPTIDX",
            "instrument": "Index Options",
            "contract": "FINNIFTY 05-Apr-2022",
            "expiryDate": "05-Apr-2022",
            "optionType": "Put",
            "strikePrice": 16500,
            "lastPrice": 29,
            "change": -11,
            "pChange": -27.5,
            "volume": 200,
            "totalTurnover": 7195.999999999999,
            "value": 7195.999999999999,
            "premiumTurnOver": 3307196,
            "underlyingValue": 17235.7,
            "openInterest": 5,
            "noOfTrades": 5
        },
        {
            "underlying": "FINNIFTY",
            "identifier": "OPTIDXFINNIFTY05-04-2022PE17100.00",
            "instrumentType": "OPTIDX",
            "instrument": "Index Options",
            "contract": "FINNIFTY 05-Apr-2022",
            "expiryDate": "05-Apr-2022",
            "optionType": "Put",
            "strikePrice": 17100,
            "lastPrice": 144.05,
            "change": -445.85,
            "pChange": -75.58,
            "volume": 40,
            "totalTurnover": 5762,
            "value": 5762,
            "premiumTurnOver": 689762,
            "underlyingValue": 17235.7,
            "openInterest": 3,
            "noOfTrades": 1
        },
        {
            "underlying": "FINNIFTY",
            "identifier": "OPTIDXFINNIFTY05-04-2022CE17400.00",
            "instrumentType": "OPTIDX",
            "instrument": "Index Options",
            "contract": "FINNIFTY 05-Apr-2022",
            "expiryDate": "05-Apr-2022",
            "optionType": "Call",
            "strikePrice": 17400,
            "lastPrice": 142.25,
            "change": -1144.75,
            "pChange": -88.95,
            "volume": 200,
            "totalTurnover": 27982,
            "value": 27982,
            "premiumTurnOver": 3507982,
            "underlyingValue": 17235.7,
            "openInterest": 0,
            "noOfTrades": 0
        },
        {
            "underlying": "FINNIFTY",
            "identifier": "OPTIDXFINNIFTY05-04-2022CE18900.00",
            "instrumentType": "OPTIDX",
            "instrument": "Index Options",
            "contract": "FINNIFTY 05-Apr-2022",
            "expiryDate": "05-Apr-2022",
            "optionType": "Call",
            "strikePrice": 18900,
            "lastPrice": 2,
            "change": -562.2,
            "pChange": -99.65,
            "volume": 400,
            "totalTurnover": 5400,
            "value": 5400,
            "premiumTurnOver": 7565400,
            "underlyingValue": 17235.7,
            "openInterest": 0,
            "noOfTrades": 0
        },
        {
            "underlying": "FINNIFTY",
            "identifier": "OPTIDXFINNIFTY05-04-2022PE17300.00",
            "instrumentType": "OPTIDX",
            "instrument": "Index Options",
            "contract": "FINNIFTY 05-Apr-2022",
            "expiryDate": "05-Apr-2022",
            "optionType": "Put",
            "strikePrice": 17300,
            "lastPrice": 240.05,
            "change": -224.3,
            "pChange": -48.3,
            "volume": 80,
            "totalTurnover": 19605.6,
            "value": 19605.6,
            "premiumTurnOver": 1403605.6,
            "underlyingValue": 17235.7,
            "openInterest": 0,
            "noOfTrades": 0
        },
        {
            "underlying": "FINNIFTY",
            "identifier": "OPTIDXFINNIFTY05-04-2022PE17200.00",
            "instrumentType": "OPTIDX",
            "instrument": "Index Options",
            "contract": "FINNIFTY 05-Apr-2022",
            "expiryDate": "05-Apr-2022",
            "optionType": "Put",
            "strikePrice": 17200,
            "lastPrice": 188.95,
            "change": -240.8,
            "pChange": -56.03,
            "volume": 40,
            "totalTurnover": 7558,
            "value": 7558,
            "premiumTurnOver": 695558,
            "underlyingValue": 17235.7,
            "openInterest": 0,
            "noOfTrades": 0
        },
        {
            "underlying": "FINNIFTY",
            "identifier": "OPTIDXFINNIFTY05-04-2022PE18200.00",
            "instrumentType": "OPTIDX",
            "instrument": "Index Options",
            "contract": "FINNIFTY 05-Apr-2022",
            "expiryDate": "05-Apr-2022",
            "optionType": "Put",
            "strikePrice": 18200,
            "lastPrice": 0,
            "change": 0,
            "pChange": 0,
            "volume": 0,
            "totalTurnover": 0,
            "value": 0,
            "premiumTurnOver": 0,
            "underlyingValue": 17235.7,
            "openInterest": 0,
            "noOfTrades": 0
        },
        {
            "underlying": "FINNIFTY",
            "identifier": "OPTIDXFINNIFTY05-04-2022PE17400.00",
            "instrumentType": "OPTIDX",
            "instrument": "Index Options",
            "contract": "FINNIFTY 05-Apr-2022",
            "expiryDate": "05-Apr-2022",
            "optionType": "Put",
            "strikePrice": 17400,
            "lastPrice": 0,
            "change": 0,
            "pChange": 0,
            "volume": 0,
            "totalTurnover": 0,
            "value": 0,
            "premiumTurnOver": 0,
            "underlyingValue": 17235.7,
            "openInterest": 0,
            "noOfTrades": 0
        },
        {
            "underlying": "FINNIFTY",
            "identifier": "OPTIDXFINNIFTY05-04-2022CE17000.00",
            "instrumentType": "OPTIDX",
            "instrument": "Index Options",
            "contract": "FINNIFTY 05-Apr-2022",
            "expiryDate": "05-Apr-2022",
            "optionType": "Call",
            "strikePrice": 17000,
            "lastPrice": 0,
            "change": 0,
            "pChange": 0,
            "volume": 0,
            "totalTurnover": 0,
            "value": 0,
            "premiumTurnOver": 0,
            "underlyingValue": 17235.7,
            "openInterest": 0,
            "noOfTrades": 0
        },
        {
            "underlying": "FINNIFTY",
            "identifier": "OPTIDXFINNIFTY05-04-2022PE16600.00",
            "instrumentType": "OPTIDX",
            "instrument": "Index Options",
            "contract": "FINNIFTY 05-Apr-2022",
            "expiryDate": "05-Apr-2022",
            "optionType": "Put",
            "strikePrice": 16600,
            "lastPrice": 0,
            "change": 0,
            "pChange": 0,
            "volume": 0,
            "totalTurnover": 0,
            "value": 0,
            "premiumTurnOver": 0,
            "underlyingValue": 17235.7,
            "openInterest": 2,
            "noOfTrades": 0
        },
        {
            "underlying": "FINNIFTY",
            "identifier": "OPTIDXFINNIFTY05-04-2022CE16200.00",
            "instrumentType": "OPTIDX",
            "instrument": "Index Options",
            "contract": "FINNIFTY 05-Apr-2022",
            "expiryDate": "05-Apr-2022",
            "optionType": "Call",
            "strikePrice": 16200,
            "lastPrice": 0,
            "change": 0,
            "pChange": 0,
            "volume": 0,
            "totalTurnover": 0,
            "value": 0,
            "premiumTurnOver": 0,
            "underlyingValue": 17235.7,
            "openInterest": 0,
            "noOfTrades": 0
        },
        {
            "underlying": "FINNIFTY",
            "identifier": "OPTIDXFINNIFTY05-04-2022CE16700.00",
            "instrumentType": "OPTIDX",
            "instrument": "Index Options",
            "contract": "FINNIFTY 05-Apr-2022",
            "expiryDate": "05-Apr-2022",
            "optionType": "Call",
            "strikePrice": 16700,
            "lastPrice": 0,
            "change": 0,
            "pChange": 0,
            "volume": 0,
            "totalTurnover": 0,
            "value": 0,
            "premiumTurnOver": 0,
            "underlyingValue": 17235.7,
            "openInterest": 0,
            "noOfTrades": 0
        },
        {
            "underlying": "FINNIFTY",
            "identifier": "OPTIDXFINNIFTY05-04-2022CE15900.00",
            "instrumentType": "OPTIDX",
            "instrument": "Index Options",
            "contract": "FINNIFTY 05-Apr-2022",
            "expiryDate": "05-Apr-2022",
            "optionType": "Call",
            "strikePrice": 15900,
            "lastPrice": 0,
            "change": 0,
            "pChange": 0,
            "volume": 0,
            "totalTurnover": 0,
            "value": 0,
            "premiumTurnOver": 0,
            "underlyingValue": 17235.7,
            "openInterest": 0,
            "noOfTrades": 0
        },
        {
            "underlying": "FINNIFTY",
            "identifier": "OPTIDXFINNIFTY12-04-2022PE16000.00",
            "instrumentType": "OPTIDX",
            "instrument": "Index Options",
            "contract": "FINNIFTY 12-Apr-2022",
            "expiryDate": "12-Apr-2022",
            "optionType": "Put",
            "strikePrice": 16000,
            "lastPrice": 0,
            "change": 0,
            "pChange": 0,
            "volume": 0,
            "totalTurnover": 0,
            "value": 0,
            "premiumTurnOver": 0,
            "underlyingValue": 17235.7,
            "openInterest": 0,
            "noOfTrades": 0
        },
        {
            "underlying": "FINNIFTY",
            "identifier": "OPTIDXFINNIFTY05-04-2022PE18300.00",
            "instrumentType": "OPTIDX",
            "instrument": "Index Options",
            "contract": "FINNIFTY 05-Apr-2022",
            "expiryDate": "05-Apr-2022",
            "optionType": "Put",
            "strikePrice": 18300,
            "lastPrice": 0,
            "change": 0,
            "pChange": 0,
            "volume": 0,
            "totalTurnover": 0,
            "value": 0,
            "premiumTurnOver": 0,
            "underlyingValue": 17235.7,
            "openInterest": 0,
            "noOfTrades": 0
        },
        {
            "underlying": "FINNIFTY",
            "identifier": "OPTIDXFINNIFTY05-04-2022CE16100.00",
            "instrumentType": "OPTIDX",
            "instrument": "Index Options",
            "contract": "FINNIFTY 05-Apr-2022",
            "expiryDate": "05-Apr-2022",
            "optionType": "Call",
            "strikePrice": 16100,
            "lastPrice": 0,
            "change": 0,
            "pChange": 0,
            "volume": 0,
            "totalTurnover": 0,
            "value": 0,
            "premiumTurnOver": 0,
            "underlyingValue": 17235.7,
            "openInterest": 0,
            "noOfTrades": 0
        },
        {
            "underlying": "FINNIFTY",
            "identifier": "OPTIDXFINNIFTY05-04-2022PE17900.00",
            "instrumentType": "OPTIDX",
            "instrument": "Index Options",
            "contract": "FINNIFTY 05-Apr-2022",
            "expiryDate": "05-Apr-2022",
            "optionType": "Put",
            "strikePrice": 17900,
            "lastPrice": 0,
            "change": 0,
            "pChange": 0,
            "volume": 0,
            "totalTurnover": 0,
            "value": 0,
            "premiumTurnOver": 0,
            "underlyingValue": 17235.7,
            "openInterest": 0,
            "noOfTrades": 0
        },
        {
            "underlying": "FINNIFTY",
            "identifier": "OPTIDXFINNIFTY12-04-2022PE15600.00",
            "instrumentType": "OPTIDX",
            "instrument": "Index Options",
            "contract": "FINNIFTY 12-Apr-2022",
            "expiryDate": "12-Apr-2022",
            "optionType": "Put",
            "strikePrice": 15600,
            "lastPrice": 0,
            "change": 0,
            "pChange": 0,
            "volume": 0,
            "totalTurnover": 0,
            "value": 0,
            "premiumTurnOver": 0,
            "underlyingValue": 17235.7,
            "openInterest": 0,
            "noOfTrades": 0
        },
        {
            "underlying": "FINNIFTY",
            "identifier": "OPTIDXFINNIFTY05-04-2022PE17500.00",
            "instrumentType": "OPTIDX",
            "instrument": "Index Options",
            "contract": "FINNIFTY 05-Apr-2022",
            "expiryDate": "05-Apr-2022",
            "optionType": "Put",
            "strikePrice": 17500,
            "lastPrice": 0,
            "change": 0,
            "pChange": 0,
            "volume": 0,
            "totalTurnover": 0,
            "value": 0,
            "premiumTurnOver": 0,
            "underlyingValue": 17235.7,
            "openInterest": 0,
            "noOfTrades": 0
        },
        {
            "underlying": "FINNIFTY",
            "identifier": "OPTIDXFINNIFTY05-04-2022PE16100.00",
            "instrumentType": "OPTIDX",
            "instrument": "Index Options",
            "contract": "FINNIFTY 05-Apr-2022",
            "expiryDate": "05-Apr-2022",
            "optionType": "Put",
            "strikePrice": 16100,
            "lastPrice": 0,
            "change": 0,
            "pChange": 0,
            "volume": 0,
            "totalTurnover": 0,
            "value": 0,
            "premiumTurnOver": 0,
            "underlyingValue": 17235.7,
            "openInterest": 0,
            "noOfTrades": 0
        },
        {
            "underlying": "FINNIFTY",
            "identifier": "OPTIDXFINNIFTY19-04-2022CE18500.00",
            "instrumentType": "OPTIDX",
            "instrument": "Index Options",
            "contract": "FINNIFTY 19-Apr-2022",
            "expiryDate": "19-Apr-2022",
            "optionType": "Call",
            "strikePrice": 18500,
            "lastPrice": 0,
            "change": 0,
            "pChange": 0,
            "volume": 0,
            "totalTurnover": 0,
            "value": 0,
            "premiumTurnOver": 0,
            "underlyingValue": 17235.7,
            "openInterest": 0,
            "noOfTrades": 0
        },
        {
            "underlying": "FINNIFTY",
            "identifier": "OPTIDXFINNIFTY05-04-2022CE16800.00",
            "instrumentType": "OPTIDX",
            "instrument": "Index Options",
            "contract": "FINNIFTY 05-Apr-2022",
            "expiryDate": "05-Apr-2022",
            "optionType": "Call",
            "strikePrice": 16800,
            "lastPrice": 0,
            "change": 0,
            "pChange": 0,
            "volume": 0,
            "totalTurnover": 0,
            "value": 0,
            "premiumTurnOver": 0,
            "underlyingValue": 17235.7,
            "openInterest": 0,
            "noOfTrades": 0
        },
        {
            "underlying": "FINNIFTY",
            "identifier": "OPTIDXFINNIFTY05-04-2022CE18400.00",
            "instrumentType": "OPTIDX",
            "instrument": "Index Options",
            "contract": "FINNIFTY 05-Apr-2022",
            "expiryDate": "05-Apr-2022",
            "optionType": "Call",
            "strikePrice": 18400,
            "lastPrice": 0,
            "change": 0,
            "pChange": 0,
            "volume": 0,
            "totalTurnover": 0,
            "value": 0,
            "premiumTurnOver": 0,
            "underlyingValue": 17235.7,
            "openInterest": 0,
            "noOfTrades": 0
        },
        {
            "underlying": "FINNIFTY",
            "identifier": "OPTIDXFINNIFTY05-04-2022CE16900.00",
            "instrumentType": "OPTIDX",
            "instrument": "Index Options",
            "contract": "FINNIFTY 05-Apr-2022",
            "expiryDate": "05-Apr-2022",
            "optionType": "Call",
            "strikePrice": 16900,
            "lastPrice": 0,
            "change": 0,
            "pChange": 0,
            "volume": 0,
            "totalTurnover": 0,
            "value": 0,
            "premiumTurnOver": 0,
            "underlyingValue": 17235.7,
            "openInterest": 0,
            "noOfTrades": 0
        },
        {
            "underlying": "FINNIFTY",
            "identifier": "OPTIDXFINNIFTY05-04-2022PE15900.00",
            "instrumentType": "OPTIDX",
            "instrument": "Index Options",
            "contract": "FINNIFTY 05-Apr-2022",
            "expiryDate": "05-Apr-2022",
            "optionType": "Put",
            "strikePrice": 15900,
            "lastPrice": 0,
            "change": 0,
            "pChange": 0,
            "volume": 0,
            "totalTurnover": 0,
            "value": 0,
            "premiumTurnOver": 0,
            "underlyingValue": 17235.7,
            "openInterest": 0,
            "noOfTrades": 0
        },
        {
            "underlying": "FINNIFTY",
            "identifier": "OPTIDXFINNIFTY05-04-2022PE16700.00",
            "instrumentType": "OPTIDX",
            "instrument": "Index Options",
            "contract": "FINNIFTY 05-Apr-2022",
            "expiryDate": "05-Apr-2022",
            "optionType": "Put",
            "strikePrice": 16700,
            "lastPrice": 0,
            "change": 0,
            "pChange": 0,
            "volume": 0,
            "totalTurnover": 0,
            "value": 0,
            "premiumTurnOver": 0,
            "underlyingValue": 17235.7,
            "openInterest": 1,
            "noOfTrades": 0
        },
        {
            "underlying": "FINNIFTY",
            "identifier": "OPTIDXFINNIFTY05-04-2022CE15800.00",
            "instrumentType": "OPTIDX",
            "instrument": "Index Options",
            "contract": "FINNIFTY 05-Apr-2022",
            "expiryDate": "05-Apr-2022",
            "optionType": "Call",
            "strikePrice": 15800,
            "lastPrice": 0,
            "change": 0,
            "pChange": 0,
            "volume": 0,
            "totalTurnover": 0,
            "value": 0,
            "premiumTurnOver": 0,
            "underlyingValue": 17235.7,
            "openInterest": 0,
            "noOfTrades": 0
        },
        {
            "underlying": "FINNIFTY",
            "identifier": "OPTIDXFINNIFTY05-04-2022CE16600.00",
            "instrumentType": "OPTIDX",
            "instrument": "Index Options",
            "contract": "FINNIFTY 05-Apr-2022",
            "expiryDate": "05-Apr-2022",
            "optionType": "Call",
            "strikePrice": 16600,
            "lastPrice": 0,
            "change": 0,
            "pChange": 0,
            "volume": 0,
            "totalTurnover": 0,
            "value": 0,
            "premiumTurnOver": 0,
            "underlyingValue": 17235.7,
            "openInterest": 0,
            "noOfTrades": 0
        },
        {
            "underlying": "FINNIFTY",
            "identifier": "OPTIDXFINNIFTY05-04-2022PE17000.00",
            "instrumentType": "OPTIDX",
            "instrument": "Index Options",
            "contract": "FINNIFTY 05-Apr-2022",
            "expiryDate": "05-Apr-2022",
            "optionType": "Put",
            "strikePrice": 17000,
            "lastPrice": 0,
            "change": 0,
            "pChange": 0,
            "volume": 0,
            "totalTurnover": 0,
            "value": 0,
            "premiumTurnOver": 0,
            "underlyingValue": 17235.7,
            "openInterest": 0,
            "noOfTrades": 0
        },
        {
            "underlying": "FINNIFTY",
            "identifier": "OPTIDXFINNIFTY05-04-2022PE17800.00",
            "instrumentType": "OPTIDX",
            "instrument": "Index Options",
            "contract": "FINNIFTY 05-Apr-2022",
            "expiryDate": "05-Apr-2022",
            "optionType": "Put",
            "strikePrice": 17800,
            "lastPrice": 0,
            "change": 0,
            "pChange": 0,
            "volume": 0,
            "totalTurnover": 0,
            "value": 0,
            "premiumTurnOver": 0,
            "underlyingValue": 17235.7,
            "openInterest": 0,
            "noOfTrades": 0
        },
        {
            "underlying": "FINNIFTY",
            "identifier": "OPTIDXFINNIFTY05-04-2022PE18400.00",
            "instrumentType": "OPTIDX",
            "instrument": "Index Options",
            "contract": "FINNIFTY 05-Apr-2022",
            "expiryDate": "05-Apr-2022",
            "optionType": "Put",
            "strikePrice": 18400,
            "lastPrice": 0,
            "change": 0,
            "pChange": 0,
            "volume": 0,
            "totalTurnover": 0,
            "value": 0,
            "premiumTurnOver": 0,
            "underlyingValue": 17235.7,
            "openInterest": 0,
            "noOfTrades": 0
        },
        {
            "underlying": "FINNIFTY",
            "identifier": "OPTIDXFINNIFTY05-04-2022PE18100.00",
            "instrumentType": "OPTIDX",
            "instrument": "Index Options",
            "contract": "FINNIFTY 05-Apr-2022",
            "expiryDate": "05-Apr-2022",
            "optionType": "Put",
            "strikePrice": 18100,
            "lastPrice": 0,
            "change": 0,
            "pChange": 0,
            "volume": 0,
            "totalTurnover": 0,
            "value": 0,
            "premiumTurnOver": 0,
            "underlyingValue": 17235.7,
            "openInterest": 0,
            "noOfTrades": 0
        },
        {
            "underlying": "FINNIFTY",
            "identifier": "OPTIDXFINNIFTY05-04-2022PE17600.00",
            "instrumentType": "OPTIDX",
            "instrument": "Index Options",
            "contract": "FINNIFTY 05-Apr-2022",
            "expiryDate": "05-Apr-2022",
            "optionType": "Put",
            "strikePrice": 17600,
            "lastPrice": 0,
            "change": 0,
            "pChange": 0,
            "volume": 0,
            "totalTurnover": 0,
            "value": 0,
            "premiumTurnOver": 0,
            "underlyingValue": 17235.7,
            "openInterest": 0,
            "noOfTrades": 0
        },
        {
            "underlying": "FINNIFTY",
            "identifier": "OPTIDXFINNIFTY05-04-2022CE18800.00",
            "instrumentType": "OPTIDX",
            "instrument": "Index Options",
            "contract": "FINNIFTY 05-Apr-2022",
            "expiryDate": "05-Apr-2022",
            "optionType": "Call",
            "strikePrice": 18800,
            "lastPrice": 0,
            "change": 0,
            "pChange": 0,
            "volume": 0,
            "totalTurnover": 0,
            "value": 0,
            "premiumTurnOver": 0,
            "underlyingValue": 17235.7,
            "openInterest": 0,
            "noOfTrades": 0
        },
        {
            "underlying": "FINNIFTY",
            "identifier": "OPTIDXFINNIFTY05-04-2022CE18500.00",
            "instrumentType": "OPTIDX",
            "instrument": "Index Options",
            "contract": "FINNIFTY 05-Apr-2022",
            "expiryDate": "05-Apr-2022",
            "optionType": "Call",
            "strikePrice": 18500,
            "lastPrice": 0,
            "change": 0,
            "pChange": 0,
            "volume": 0,
            "totalTurnover": 0,
            "value": 0,
            "premiumTurnOver": 0,
            "underlyingValue": 17235.7,
            "openInterest": 0,
            "noOfTrades": 0
        },
        {
            "underlying": "FINNIFTY",
            "identifier": "OPTIDXFINNIFTY12-04-2022PE16100.00",
            "instrumentType": "OPTIDX",
            "instrument": "Index Options",
            "contract": "FINNIFTY 12-Apr-2022",
            "expiryDate": "12-Apr-2022",
            "optionType": "Put",
            "strikePrice": 16100,
            "lastPrice": 170,
            "change": -59.95,
            "pChange": -26.07,
            "volume": 240,
            "totalTurnover": 40800,
            "value": 40800,
            "premiumTurnOver": 3904800,
            "underlyingValue": 17235.7,
            "openInterest": 0,
            "noOfTrades": 0
        },
        {
            "underlying": "FINNIFTY",
            "identifier": "OPTIDXFINNIFTY05-04-2022CE19000.00",
            "instrumentType": "OPTIDX",
            "instrument": "Index Options",
            "contract": "FINNIFTY 05-Apr-2022",
            "expiryDate": "05-Apr-2022",
            "optionType": "Call",
            "strikePrice": 19000,
            "lastPrice": 0,
            "change": 0,
            "pChange": 0,
            "volume": 0,
            "totalTurnover": 0,
            "value": 0,
            "premiumTurnOver": 0,
            "underlyingValue": 17235.7,
            "openInterest": 0,
            "noOfTrades": 0
        },
        {
            "underlying": "FINNIFTY",
            "identifier": "OPTIDXFINNIFTY05-04-2022CE18200.00",
            "instrumentType": "OPTIDX",
            "instrument": "Index Options",
            "contract": "FINNIFTY 05-Apr-2022",
            "expiryDate": "05-Apr-2022",
            "optionType": "Call",
            "strikePrice": 18200,
            "lastPrice": 0,
            "change": 0,
            "pChange": 0,
            "volume": 0,
            "totalTurnover": 0,
            "value": 0,
            "premiumTurnOver": 0,
            "underlyingValue": 17235.7,
            "openInterest": 0,
            "noOfTrades": 0
        },
        {
            "underlying": "FINNIFTY",
            "identifier": "OPTIDXFINNIFTY05-04-2022PE16200.00",
            "instrumentType": "OPTIDX",
            "instrument": "Index Options",
            "contract": "FINNIFTY 05-Apr-2022",
            "expiryDate": "05-Apr-2022",
            "optionType": "Put",
            "strikePrice": 16200,
            "lastPrice": 0,
            "change": 0,
            "pChange": 0,
            "volume": 0,
            "totalTurnover": 0,
            "value": 0,
            "premiumTurnOver": 0,
            "underlyingValue": 17235.7,
            "openInterest": 0,
            "noOfTrades": 0
        },
        {
            "underlying": "FINNIFTY",
            "identifier": "OPTIDXFINNIFTY05-04-2022CE17100.00",
            "instrumentType": "OPTIDX",
            "instrument": "Index Options",
            "contract": "FINNIFTY 05-Apr-2022",
            "expiryDate": "05-Apr-2022",
            "optionType": "Call",
            "strikePrice": 17100,
            "lastPrice": 0,
            "change": 0,
            "pChange": 0,
            "volume": 0,
            "totalTurnover": 0,
            "value": 0,
            "premiumTurnOver": 0,
            "underlyingValue": 17235.7,
            "openInterest": 0,
            "noOfTrades": 0
        },
        {
            "underlying": "FINNIFTY",
            "identifier": "OPTIDXFINNIFTY05-04-2022CE16300.00",
            "instrumentType": "OPTIDX",
            "instrument": "Index Options",
            "contract": "FINNIFTY 05-Apr-2022",
            "expiryDate": "05-Apr-2022",
            "optionType": "Call",
            "strikePrice": 16300,
            "lastPrice": 0,
            "change": 0,
            "pChange": 0,
            "volume": 0,
            "totalTurnover": 0,
            "value": 0,
            "premiumTurnOver": 0,
            "underlyingValue": 17235.7,
            "openInterest": 0,
            "noOfTrades": 0
        },
        {
            "underlying": "FINNIFTY",
            "identifier": "OPTIDXFINNIFTY05-04-2022CE16000.00",
            "instrumentType": "OPTIDX",
            "instrument": "Index Options",
            "contract": "FINNIFTY 05-Apr-2022",
            "expiryDate": "05-Apr-2022",
            "optionType": "Call",
            "strikePrice": 16000,
            "lastPrice": 0,
            "change": 0,
            "pChange": 0,
            "volume": 0,
            "totalTurnover": 0,
            "value": 0,
            "premiumTurnOver": 0,
            "underlyingValue": 17235.7,
            "openInterest": 0,
            "noOfTrades": 0
        },
        {
            "underlying": "FINNIFTY",
            "identifier": "OPTIDXFINNIFTY05-04-2022CE15500.00",
            "instrumentType": "OPTIDX",
            "instrument": "Index Options",
            "contract": "FINNIFTY 05-Apr-2022",
            "expiryDate": "05-Apr-2022",
            "optionType": "Call",
            "strikePrice": 15500,
            "lastPrice": 0,
            "change": 0,
            "pChange": 0,
            "volume": 0,
            "totalTurnover": 0,
            "value": 0,
            "premiumTurnOver": 0,
            "underlyingValue": 17235.7,
            "openInterest": 0,
            "noOfTrades": 0
        },
        {
            "underlying": "FINNIFTY",
            "identifier": "OPTIDXFINNIFTY05-04-2022PE17700.00",
            "instrumentType": "OPTIDX",
            "instrument": "Index Options",
            "contract": "FINNIFTY 05-Apr-2022",
            "expiryDate": "05-Apr-2022",
            "optionType": "Put",
            "strikePrice": 17700,
            "lastPrice": 0,
            "change": 0,
            "pChange": 0,
            "volume": 0,
            "totalTurnover": 0,
            "value": 0,
            "premiumTurnOver": 0,
            "underlyingValue": 17235.7,
            "openInterest": 0,
            "noOfTrades": 0
        },
        {
            "underlying": "FINNIFTY",
            "identifier": "OPTIDXFINNIFTY12-04-2022CE18100.00",
            "instrumentType": "OPTIDX",
            "instrument": "Index Options",
            "contract": "FINNIFTY 12-Apr-2022",
            "expiryDate": "12-Apr-2022",
            "optionType": "Call",
            "strikePrice": 18100,
            "lastPrice": 0,
            "change": 0,
            "pChange": 0,
            "volume": 0,
            "totalTurnover": 0,
            "value": 0,
            "premiumTurnOver": 0,
            "underlyingValue": 17235.7,
            "openInterest": 7,
            "noOfTrades": 0
        },
        {
            "underlying": "FINNIFTY",
            "identifier": "OPTIDXFINNIFTY05-04-2022CE17300.00",
            "instrumentType": "OPTIDX",
            "instrument": "Index Options",
            "contract": "FINNIFTY 05-Apr-2022",
            "expiryDate": "05-Apr-2022",
            "optionType": "Call",
            "strikePrice": 17300,
            "lastPrice": 0,
            "change": 0,
            "pChange": 0,
            "volume": 0,
            "totalTurnover": 0,
            "value": 0,
            "premiumTurnOver": 0,
            "underlyingValue": 17235.7,
            "openInterest": 0,
            "noOfTrades": 0
        },
        {
            "underlying": "FINNIFTY",
            "identifier": "OPTIDXFINNIFTY05-04-2022CE18700.00",
            "instrumentType": "OPTIDX",
            "instrument": "Index Options",
            "contract": "FINNIFTY 05-Apr-2022",
            "expiryDate": "05-Apr-2022",
            "optionType": "Call",
            "strikePrice": 18700,
            "lastPrice": 0,
            "change": 0,
            "pChange": 0,
            "volume": 0,
            "totalTurnover": 0,
            "value": 0,
            "premiumTurnOver": 0,
            "underlyingValue": 17235.7,
            "openInterest": 0,
            "noOfTrades": 0
        },
        {
            "underlying": "FINNIFTY",
            "identifier": "OPTIDXFINNIFTY12-04-2022PE15400.00",
            "instrumentType": "OPTIDX",
            "instrument": "Index Options",
            "contract": "FINNIFTY 12-Apr-2022",
            "expiryDate": "12-Apr-2022",
            "optionType": "Put",
            "strikePrice": 15400,
            "lastPrice": 0,
            "change": 0,
            "pChange": 0,
            "volume": 0,
            "totalTurnover": 0,
            "value": 0,
            "premiumTurnOver": 0,
            "underlyingValue": 17235.7,
            "openInterest": 0,
            "noOfTrades": 0
        },
        {
            "underlying": "FINNIFTY",
            "identifier": "OPTIDXFINNIFTY05-04-2022CE18100.00",
            "instrumentType": "OPTIDX",
            "instrument": "Index Options",
            "contract": "FINNIFTY 05-Apr-2022",
            "expiryDate": "05-Apr-2022",
            "optionType": "Call",
            "strikePrice": 18100,
            "lastPrice": 0,
            "change": 0,
            "pChange": 0,
            "volume": 0,
            "totalTurnover": 0,
            "value": 0,
            "premiumTurnOver": 0,
            "underlyingValue": 17235.7,
            "openInterest": 0,
            "noOfTrades": 0
        },
        {
            "underlying": "FINNIFTY",
            "identifier": "OPTIDXFINNIFTY26-04-2022CE16500.00",
            "instrumentType": "OPTIDX",
            "instrument": "Index Options",
            "contract": "FINNIFTY 26-Apr-2022",
            "expiryDate": "26-Apr-2022",
            "optionType": "Call",
            "strikePrice": 16500,
            "lastPrice": 0,
            "change": 0,
            "pChange": 0,
            "volume": 0,
            "totalTurnover": 0,
            "value": 0,
            "premiumTurnOver": 0,
            "underlyingValue": 17235.7,
            "openInterest": 0,
            "noOfTrades": 0
        },
        {
            "underlying": "FINNIFTY",
            "identifier": "OPTIDXFINNIFTY05-04-2022CE15600.00",
            "instrumentType": "OPTIDX",
            "instrument": "Index Options",
            "contract": "FINNIFTY 05-Apr-2022",
            "expiryDate": "05-Apr-2022",
            "optionType": "Call",
            "strikePrice": 15600,
            "lastPrice": 0,
            "change": 0,
            "pChange": 0,
            "volume": 0,
            "totalTurnover": 0,
            "value": 0,
            "premiumTurnOver": 0,
            "underlyingValue": 17235.7,
            "openInterest": 0,
            "noOfTrades": 0
        },
        {
            "underlying": "FINNIFTY",
            "identifier": "OPTIDXFINNIFTY05-04-2022PE16300.00",
            "instrumentType": "OPTIDX",
            "instrument": "Index Options",
            "contract": "FINNIFTY 05-Apr-2022",
            "expiryDate": "05-Apr-2022",
            "optionType": "Put",
            "strikePrice": 16300,
            "lastPrice": 0,
            "change": 0,
            "pChange": 0,
            "volume": 0,
            "totalTurnover": 0,
            "value": 0,
            "premiumTurnOver": 0,
            "underlyingValue": 17235.7,
            "openInterest": 0,
            "noOfTrades": 0
        },
        {
            "underlying": "FINNIFTY",
            "identifier": "OPTIDXFINNIFTY05-04-2022PE15500.00",
            "instrumentType": "OPTIDX",
            "instrument": "Index Options",
            "contract": "FINNIFTY 05-Apr-2022",
            "expiryDate": "05-Apr-2022",
            "optionType": "Put",
            "strikePrice": 15500,
            "lastPrice": 0,
            "change": 0,
            "pChange": 0,
            "volume": 0,
            "totalTurnover": 0,
            "value": 0,
            "premiumTurnOver": 0,
            "underlyingValue": 17235.7,
            "openInterest": 0,
            "noOfTrades": 0
        },
        {
            "underlying": "FINNIFTY",
            "identifier": "OPTIDXFINNIFTY05-04-2022CE16400.00",
            "instrumentType": "OPTIDX",
            "instrument": "Index Options",
            "contract": "FINNIFTY 05-Apr-2022",
            "expiryDate": "05-Apr-2022",
            "optionType": "Call",
            "strikePrice": 16400,
            "lastPrice": 0,
            "change": 0,
            "pChange": 0,
            "volume": 0,
            "totalTurnover": 0,
            "value": 0,
            "premiumTurnOver": 0,
            "underlyingValue": 17235.7,
            "openInterest": 0,
            "noOfTrades": 0
        },
        {
            "underlying": "FINNIFTY",
            "identifier": "OPTIDXFINNIFTY26-04-2022CE16000.00",
            "instrumentType": "OPTIDX",
            "instrument": "Index Options",
            "contract": "FINNIFTY 26-Apr-2022",
            "expiryDate": "26-Apr-2022",
            "optionType": "Call",
            "strikePrice": 16000,
            "lastPrice": 0,
            "change": 0,
            "pChange": 0,
            "volume": 0,
            "totalTurnover": 0,
            "value": 0,
            "premiumTurnOver": 0,
            "underlyingValue": 17235.7,
            "openInterest": 0,
            "noOfTrades": 0
        },
        {
            "underlying": "FINNIFTY",
            "identifier": "OPTIDXFINNIFTY05-04-2022PE16800.00",
            "instrumentType": "OPTIDX",
            "instrument": "Index Options",
            "contract": "FINNIFTY 05-Apr-2022",
            "expiryDate": "05-Apr-2022",
            "optionType": "Put",
            "strikePrice": 16800,
            "lastPrice": 0,
            "change": 0,
            "pChange": 0,
            "volume": 0,
            "totalTurnover": 0,
            "value": 0,
            "premiumTurnOver": 0,
            "underlyingValue": 17235.7,
            "openInterest": 2,
            "noOfTrades": 0
        },
        {
            "underlying": "FINNIFTY",
            "identifier": "OPTIDXFINNIFTY26-04-2022CE17300.00",
            "instrumentType": "OPTIDX",
            "instrument": "Index Options",
            "contract": "FINNIFTY 26-Apr-2022",
            "expiryDate": "26-Apr-2022",
            "optionType": "Call",
            "strikePrice": 17300,
            "lastPrice": 0,
            "change": 0,
            "pChange": 0,
            "volume": 0,
            "totalTurnover": 0,
            "value": 0,
            "premiumTurnOver": 0,
            "underlyingValue": 17235.7,
            "openInterest": 0,
            "noOfTrades": 0
        },
        {
            "underlying": "FINNIFTY",
            "identifier": "OPTIDXFINNIFTY05-04-2022CE15700.00",
            "instrumentType": "OPTIDX",
            "instrument": "Index Options",
            "contract": "FINNIFTY 05-Apr-2022",
            "expiryDate": "05-Apr-2022",
            "optionType": "Call",
            "strikePrice": 15700,
            "lastPrice": 0,
            "change": 0,
            "pChange": 0,
            "volume": 0,
            "totalTurnover": 0,
            "value": 0,
            "premiumTurnOver": 0,
            "underlyingValue": 17235.7,
            "openInterest": 0,
            "noOfTrades": 0
        },
        {
            "underlying": "FINNIFTY",
            "identifier": "OPTIDXFINNIFTY12-04-2022PE15900.00",
            "instrumentType": "OPTIDX",
            "instrument": "Index Options",
            "contract": "FINNIFTY 12-Apr-2022",
            "expiryDate": "12-Apr-2022",
            "optionType": "Put",
            "strikePrice": 15900,
            "lastPrice": 0,
            "change": 0,
            "pChange": 0,
            "volume": 0,
            "totalTurnover": 0,
            "value": 0,
            "premiumTurnOver": 0,
            "underlyingValue": 17235.7,
            "openInterest": 0,
            "noOfTrades": 0
        },
        {
            "underlying": "FINNIFTY",
            "identifier": "OPTIDXFINNIFTY05-04-2022CE16500.00",
            "instrumentType": "OPTIDX",
            "instrument": "Index Options",
            "contract": "FINNIFTY 05-Apr-2022",
            "expiryDate": "05-Apr-2022",
            "optionType": "Call",
            "strikePrice": 16500,
            "lastPrice": 0,
            "change": 0,
            "pChange": 0,
            "volume": 0,
            "totalTurnover": 0,
            "value": 0,
            "premiumTurnOver": 0,
            "underlyingValue": 17235.7,
            "openInterest": 0,
            "noOfTrades": 0
        },
        {
            "underlying": "FINNIFTY",
            "identifier": "OPTIDXFINNIFTY05-04-2022CE17900.00",
            "instrumentType": "OPTIDX",
            "instrument": "Index Options",
            "contract": "FINNIFTY 05-Apr-2022",
            "expiryDate": "05-Apr-2022",
            "optionType": "Call",
            "strikePrice": 17900,
            "lastPrice": 0,
            "change": 0,
            "pChange": 0,
            "volume": 0,
            "totalTurnover": 0,
            "value": 0,
            "premiumTurnOver": 0,
            "underlyingValue": 17235.7,
            "openInterest": 0,
            "noOfTrades": 0
        },
        {
            "underlying": "FINNIFTY",
            "identifier": "OPTIDXFINNIFTY05-04-2022PE18000.00",
            "instrumentType": "OPTIDX",
            "instrument": "Index Options",
            "contract": "FINNIFTY 05-Apr-2022",
            "expiryDate": "05-Apr-2022",
            "optionType": "Put",
            "strikePrice": 18000,
            "lastPrice": 0,
            "change": 0,
            "pChange": 0,
            "volume": 0,
            "totalTurnover": 0,
            "value": 0,
            "premiumTurnOver": 0,
            "underlyingValue": 17235.7,
            "openInterest": 0,
            "noOfTrades": 0
        },
        {
            "underlying": "FINNIFTY",
            "identifier": "OPTIDXFINNIFTY05-04-2022PE16400.00",
            "instrumentType": "OPTIDX",
            "instrument": "Index Options",
            "contract": "FINNIFTY 05-Apr-2022",
            "expiryDate": "05-Apr-2022",
            "optionType": "Put",
            "strikePrice": 16400,
            "lastPrice": 0,
            "change": 0,
            "pChange": 0,
            "volume": 0,
            "totalTurnover": 0,
            "value": 0,
            "premiumTurnOver": 0,
            "underlyingValue": 17235.7,
            "openInterest": 0,
            "noOfTrades": 0
        },
        {
            "underlying": "FINNIFTY",
            "identifier": "OPTIDXFINNIFTY26-04-2022PE16500.00",
            "instrumentType": "OPTIDX",
            "instrument": "Index Options",
            "contract": "FINNIFTY 26-Apr-2022",
            "expiryDate": "26-Apr-2022",
            "optionType": "Put",
            "strikePrice": 16500,
            "lastPrice": 0,
            "change": 0,
            "pChange": 0,
            "volume": 0,
            "totalTurnover": 0,
            "value": 0,
            "premiumTurnOver": 0,
            "underlyingValue": 17235.7,
            "openInterest": 0,
            "noOfTrades": 0
        },
        {
            "underlying": "FINNIFTY",
            "identifier": "OPTIDXFINNIFTY26-04-2022PE16800.00",
            "instrumentType": "OPTIDX",
            "instrument": "Index Options",
            "contract": "FINNIFTY 26-Apr-2022",
            "expiryDate": "26-Apr-2022",
            "optionType": "Put",
            "strikePrice": 16800,
            "lastPrice": 0,
            "change": 0,
            "pChange": 0,
            "volume": 0,
            "totalTurnover": 0,
            "value": 0,
            "premiumTurnOver": 0,
            "underlyingValue": 17235.7,
            "openInterest": 0,
            "noOfTrades": 0
        },
        {
            "underlying": "FINNIFTY",
            "identifier": "OPTIDXFINNIFTY05-04-2022CE19100.00",
            "instrumentType": "OPTIDX",
            "instrument": "Index Options",
            "contract": "FINNIFTY 05-Apr-2022",
            "expiryDate": "05-Apr-2022",
            "optionType": "Call",
            "strikePrice": 19100,
            "lastPrice": 0,
            "change": 0,
            "pChange": 0,
            "volume": 0,
            "totalTurnover": 0,
            "value": 0,
            "premiumTurnOver": 0,
            "underlyingValue": 17235.7,
            "openInterest": 0,
            "noOfTrades": 0
        },
        {
            "underlying": "FINNIFTY",
            "identifier": "OPTIDXFINNIFTY05-04-2022CE18300.00",
            "instrumentType": "OPTIDX",
            "instrument": "Index Options",
            "contract": "FINNIFTY 05-Apr-2022",
            "expiryDate": "05-Apr-2022",
            "optionType": "Call",
            "strikePrice": 18300,
            "lastPrice": 0,
            "change": 0,
            "pChange": 0,
            "volume": 0,
            "totalTurnover": 0,
            "value": 0,
            "premiumTurnOver": 0,
            "underlyingValue": 17235.7,
            "openInterest": 0,
            "noOfTrades": 0
        },
        {
            "underlying": "FINNIFTY",
            "identifier": "OPTIDXFINNIFTY05-04-2022CE17200.00",
            "instrumentType": "OPTIDX",
            "instrument": "Index Options",
            "contract": "FINNIFTY 05-Apr-2022",
            "expiryDate": "05-Apr-2022",
            "optionType": "Call",
            "strikePrice": 17200,
            "lastPrice": 0,
            "change": 0,
            "pChange": 0,
            "volume": 0,
            "totalTurnover": 0,
            "value": 0,
            "premiumTurnOver": 0,
            "underlyingValue": 17235.7,
            "openInterest": 0,
            "noOfTrades": 0
        },
        {
            "underlying": "FINNIFTY",
            "identifier": "OPTIDXFINNIFTY12-04-2022CE18800.00",
            "instrumentType": "OPTIDX",
            "instrument": "Index Options",
            "contract": "FINNIFTY 12-Apr-2022",
            "expiryDate": "12-Apr-2022",
            "optionType": "Call",
            "strikePrice": 18800,
            "lastPrice": 0,
            "change": 0,
            "pChange": 0,
            "volume": 0,
            "totalTurnover": 0,
            "value": 0,
            "premiumTurnOver": 0,
            "underlyingValue": 17235.7,
            "openInterest": 0,
            "noOfTrades": 0
        },
        {
            "underlying": "FINNIFTY",
            "identifier": "OPTIDXFINNIFTY12-04-2022CE19000.00",
            "instrumentType": "OPTIDX",
            "instrument": "Index Options",
            "contract": "FINNIFTY 12-Apr-2022",
            "expiryDate": "12-Apr-2022",
            "optionType": "Call",
            "strikePrice": 19000,
            "lastPrice": 0,
            "change": 0,
            "pChange": 0,
            "volume": 0,
            "totalTurnover": 0,
            "value": 0,
            "premiumTurnOver": 0,
            "underlyingValue": 17235.7,
            "openInterest": 0,
            "noOfTrades": 0
        },
        {
            "underlying": "FINNIFTY",
            "identifier": "OPTIDXFINNIFTY05-04-2022CE18600.00",
            "instrumentType": "OPTIDX",
            "instrument": "Index Options",
            "contract": "FINNIFTY 05-Apr-2022",
            "expiryDate": "05-Apr-2022",
            "optionType": "Call",
            "strikePrice": 18600,
            "lastPrice": 0,
            "change": 0,
            "pChange": 0,
            "volume": 0,
            "totalTurnover": 0,
            "value": 0,
            "premiumTurnOver": 0,
            "underlyingValue": 17235.7,
            "openInterest": 0,
            "noOfTrades": 0
        },
        {
            "underlying": "FINNIFTY",
            "identifier": "OPTIDXFINNIFTY05-04-2022CE17800.00",
            "instrumentType": "OPTIDX",
            "instrument": "Index Options",
            "contract": "FINNIFTY 05-Apr-2022",
            "expiryDate": "05-Apr-2022",
            "optionType": "Call",
            "strikePrice": 17800,
            "lastPrice": 0,
            "change": 0,
            "pChange": 0,
            "volume": 0,
            "totalTurnover": 0,
            "value": 0,
            "premiumTurnOver": 0,
            "underlyingValue": 17235.7,
            "openInterest": 0,
            "noOfTrades": 0
        },
        {
            "underlying": "FINNIFTY",
            "identifier": "OPTIDXFINNIFTY05-04-2022PE15800.00",
            "instrumentType": "OPTIDX",
            "instrument": "Index Options",
            "contract": "FINNIFTY 05-Apr-2022",
            "expiryDate": "05-Apr-2022",
            "optionType": "Put",
            "strikePrice": 15800,
            "lastPrice": 0,
            "change": 0,
            "pChange": 0,
            "volume": 0,
            "totalTurnover": 0,
            "value": 0,
            "premiumTurnOver": 0,
            "underlyingValue": 17235.7,
            "openInterest": 0,
            "noOfTrades": 0
        },
        {
            "underlying": "FINNIFTY",
            "identifier": "OPTIDXFINNIFTY05-04-2022PE16900.00",
            "instrumentType": "OPTIDX",
            "instrument": "Index Options",
            "contract": "FINNIFTY 05-Apr-2022",
            "expiryDate": "05-Apr-2022",
            "optionType": "Put",
            "strikePrice": 16900,
            "lastPrice": 0,
            "change": 0,
            "pChange": 0,
            "volume": 0,
            "totalTurnover": 0,
            "value": 0,
            "premiumTurnOver": 0,
            "underlyingValue": 17235.7,
            "openInterest": 0,
            "noOfTrades": 0
        },
        {
            "underlying": "FINNIFTY",
            "identifier": "OPTIDXFINNIFTY19-04-2022PE15500.00",
            "instrumentType": "OPTIDX",
            "instrument": "Index Options",
            "contract": "FINNIFTY 19-Apr-2022",
            "expiryDate": "19-Apr-2022",
            "optionType": "Put",
            "strikePrice": 15500,
            "lastPrice": 0,
            "change": 0,
            "pChange": 0,
            "volume": 0,
            "totalTurnover": 0,
            "value": 0,
            "premiumTurnOver": 0,
            "underlyingValue": 17235.7,
            "openInterest": 2,
            "noOfTrades": 0
        }
    ],
    "timestamp": "31-Mar-2022 11:30:50",
    "marketStatus": {
        "market": "FO",
        "marketOpenOrClose": "Open",
        "marketCurrentTradingDate": "Mar 31,2022",
        "marketOpenTime": "0915",
        "marketCloseTime": "1530",
        "marketPreviousTradingDate": "Mar 30,2022",
        "marketNextTradingDate": "Apr 01,2022",
        "marketStatusMessage": "Market is Open"
    }
}