{
    "data": [
        {
            "underlying": "BANKNIFTY",
            "identifier": "FUTIDXBANKNIFTY28-07-2022XX0.00",
            "instrumentType": "FUTIDX",
            "instrument": "Index Futures",
            "contract": "BANKNIFTY 28-Jul-2022",
            "expiryDate": "28-Jul-2022",
            "optionType": "-",
            "strikePrice": 0,
            "lastPrice": 34914.35,
            "change": -252.3,
            "pChange": -0.72,
            "volume": 2783675,
            "totalTurnover": 97705489315.5,
            "value": 97705489315.5,
            "premiumTurnOver": 97705489315.5,
            "underlyingValue": 34835.7,
            "openInterest": 88954,
            "noOfTrades": 111347,
            "meta": {
                "data": [],
                "msg": "No Data Found"
            }
        },
        {
            "underlying": "BANKNIFTY",
            "identifier": "FUTIDXBANKNIFTY25-08-2022XX0.00",
            "instrumentType": "FUTIDX",
            "instrument": "Index Futures",
            "contract": "BANKNIFTY 25-Aug-2022",
            "expiryDate": "25-Aug-2022",
            "optionType": "-",
            "strikePrice": 0,
            "lastPrice": 34948.95,
            "change": -258.35,
            "pChange": -0.73,
            "volume": 141325,
            "totalTurnover": 4963865382,
            "value": 4963865382,
            "premiumTurnOver": 4963865382,
            "underlyingValue": 34816.65,
            "openInterest": 12726,
            "noOfTrades": 5622,
            "meta": {
                "data": [],
                "msg": "No Data Found"
            }
        },
        {
            "underlying": "BANKNIFTY",
            "identifier": "FUTIDXBANKNIFTY29-09-2022XX0.00",
            "instrumentType": "FUTIDX",
            "instrument": "Index Futures",
            "contract": "BANKNIFTY 29-Sep-2022",
            "expiryDate": "29-Sep-2022",
            "optionType": "-",
            "strikePrice": 0,
            "lastPrice": 35036,
            "change": -254.15,
            "pChange": -0.72,
            "volume": 34850,
            "totalTurnover": 1227806274.5,
            "value": 1227806274.5,
            "premiumTurnOver": 1227806274.5,
            "underlyingValue": 34816.65,
            "openInterest": 2054,
            "noOfTrades": 1388,
            "meta": {
                "data": [],
                "msg": "No Data Found"
            }
        }
    ],
    "timestamp": "13-Jul-2022 14:02:51",
    "marketStatus": {
        "market": "FO",
        "marketOpenOrClose": "Open",
        "marketCurrentTradingDate": "Jul 13,2022",
        "marketOpenTime": "0915",
        "marketCloseTime": "1530",
        "marketPreviousTradingDate": "Jul 12,2022",
        "marketNextTradingDate": "Jul 14,2022",
        "marketStatusMessage": "Market is Open"
    }
}